Metadata-Version: 2.1
Name: geosdem
Version: 0.0.1
Summary: A python package for demo
Home-page: https://github.com/giswr/geosdem
Author: Francis E. Oussou
Author-email: francisoussou@gmail.com
License: MIT license
Keywords: geosdem
Classifier: Intended Audience :: Developers
Classifier: License :: OSI Approved :: MIT License
Classifier: Natural Language :: English
Classifier: Programming Language :: Python :: 3
Classifier: Programming Language :: Python :: 3.8
Classifier: Programming Language :: Python :: 3.9
Classifier: Programming Language :: Python :: 3.10
Classifier: Programming Language :: Python :: 3.11
Requires-Python: >=3.8
License-File: LICENSE
